odoo/addons/user_log_view/README.rst
odoo/addons/user_log_view/__init__.py
odoo/addons/user_log_view/__manifest__.py
odoo/addons/user_log_view/i18n/user_log_view.pot
odoo/addons/user_log_view/readme/CONTRIBUTORS.rst
odoo/addons/user_log_view/readme/DESCRIPTION.rst
odoo/addons/user_log_view/readme/USAGE.rst
odoo/addons/user_log_view/static/description/icon.png
odoo/addons/user_log_view/static/description/index.html
odoo/addons/user_log_view/views/res_users_views.xml
odoo13_addon_user_log_view-13.0.1.0.1.dev2.dist-info/METADATA
odoo13_addon_user_log_view-13.0.1.0.1.dev2.dist-info/WHEEL
odoo13_addon_user_log_view-13.0.1.0.1.dev2.dist-info/top_level.txt
odoo13_addon_user_log_view-13.0.1.0.1.dev2.dist-info/RECORD
