Metadata-Version: 2.1
Name: odoo13-addon-user-log-view
Version: 13.0.1.0.1.dev2
Summary: Allow to see user's actions log
Home-page: https://github.com/OCA/server-auth
Author: IT-Projects LLC, Odoo Community Association (OCA)
Author-email: support@odoo-community.org
License: LGPL-3
Platform: UNKNOWN
Classifier: Programming Language :: Python
Classifier: Framework :: Odoo
Classifier: Framework :: Odoo :: 13.0
Classifier: License :: OSI Approved :: GNU Lesser General Public License v3 (LGPLv3)
Classifier: Development Status :: 5 - Production/Stable
Requires-Python: >=3.5
Requires-Dist: odoo <13.1dev,>=13.0a
